[
  {
    "id": 1767521516331,
    "stall": 1,
    "ulamId": 2,
    "ulamName": "Adobo",
    "price": 45,
    "withRice": true,
    "userName": "neth eqwewq",
    "userEmail": "nethh@cvsu.edu.ph",
    "createdAt": "2026-01-04T10:11:56.331Z"
  },
  {
    "id": 1767521586856,
    "stall": 1,
    "ulamId": 2,
    "ulamName": "Adobo",
    "price": 45,
    "withRice": true,
    "userName": "neth eqwewq",
    "userEmail": "nethh@cvsu.edu.ph",
    "createdAt": "2026-01-04T10:13:06.856Z"
  },
  {
    "id": 1767521637089,
    "stall": 1,
    "ulamId": 2,
    "ulamName": "Adobo",
    "price": 45,
    "withRice": true,
    "userName": "neth eqwewq",
    "userEmail": "nethh@cvsu.edu.ph",
    "createdAt": "2026-01-04T10:13:57.089Z"
  },
  {
    "id": 1767521693219,
    "stall": 1,
    "ulamId": 2,
    "ulamName": "Adobo",
    "price": 45,
    "withRice": true,
    "userName": "ward lariuo",
    "userEmail": "ward@cvsu.edu.ph",
    "createdAt": "2026-01-04T10:14:53.219Z"
  },
  {
    "id": 1767521826904,
    "stall": 2,
    "ulamId": 4,
    "ulamName": "Tonkatsu",
    "price": 65,
    "withRice": true,
    "userName": "ralph frani",
    "userEmail": "ralph.frani@cvsu.edu.ph",
    "createdAt": "2026-01-04T10:17:06.904Z"
  },
  {
    "id": 1767522251181,
    "stall": 1,
    "ulamId": 2,
    "ulamName": "Adobo",
    "price": 45,
    "withRice": true,
    "userName": "ralph frani",
    "userEmail": "ralph.frani@cvsu.edu.ph",
    "createdAt": "2026-01-04T10:24:11.181Z"
  },
  {
    "id": 1767522985988,
    "stall": 1,
    "ulamId": 1,
    "ulamName": "Caldereta",
    "price": 40,
    "withRice": false,
    "userName": "neth eqwewq",
    "userEmail": "nethh@cvsu.edu.ph",
    "createdAt": "2026-01-04T10:36:25.988Z"
  },
  {
    "id": 1767524134438,
    "stall": 1,
    "ulamId": 1,
    "ulamName": "Caldereta",
    "price": 50,
    "withRice": true,
    "userName": "neth eqwewq",
    "userEmail": "nethh@cvsu.edu.ph",
    "createdAt": "2026-01-04T10:55:34.438Z"
  },
  {
    "id": 1767524659332,
    "stall": 1,
    "ulamId": 1,
    "ulamName": "Caldereta",
    "price": 40,
    "withRice": false,
    "userName": "neth eqwewq",
    "userEmail": "nethh@cvsu.edu.ph",
    "createdAt": "2026-01-04T11:04:19.332Z"
  },
  {
    "id": 1767555031974,
    "stall": 2,
    "ulamId": 4,
    "ulamName": "Tonkatsu",
    "price": 55,
    "withRice": false,
    "userName": "neth eqwewq",
    "userEmail": "nethh@cvsu.edu.ph",
    "createdAt": "2026-01-04T19:30:31.974Z"
  },
  {
    "id": 1767555095026,
    "stall": 1,
    "ulamId": 1,
    "ulamName": "Caldereta",
    "price": 40,
    "withRice": false,
    "userName": "neth eqwewq",
    "userEmail": "nethh@cvsu.edu.ph",
    "createdAt": "2026-01-04T19:31:35.026Z"
  },
  {
    "id": 1767557809293,
    "stall": 1,
    "ulamId": 1,
    "ulamName": "Caldereta",
    "price": 40,
    "withRice": false,
    "userName": "neth eqwewq",
    "userEmail": "nethh@cvsu.edu.ph",
    "createdAt": "2026-01-04T20:16:49.293Z"
  }
]